ipecharts/__init__.py
ipecharts/_frontend.py
ipecharts/_version.py
ipecharts/baseechartswidget.py
ipecharts/basewidget.py
ipecharts/echarts.py
ipecharts/tools.py
ipecharts/option/__init__.py
ipecharts/option/angleaxis.py
ipecharts/option/aria.py
ipecharts/option/axispointer.py
ipecharts/option/basewidget.py
ipecharts/option/brush.py
ipecharts/option/calendar.py
ipecharts/option/dataset.py
ipecharts/option/datazoom.py
ipecharts/option/geo.py
ipecharts/option/geo3d.py
ipecharts/option/globe.py
ipecharts/option/graphic.py
ipecharts/option/grid.py
ipecharts/option/grid3d.py
ipecharts/option/legend.py
ipecharts/option/mapbox3d.py
ipecharts/option/matrix.py
ipecharts/option/media.py
ipecharts/option/option.py
ipecharts/option/parallel.py
ipecharts/option/parallelaxis.py
ipecharts/option/polar.py
ipecharts/option/radar.py
ipecharts/option/radiusaxis.py
ipecharts/option/series.py
ipecharts/option/singleaxis.py
ipecharts/option/stateanimation.py
ipecharts/option/textstyle.py
ipecharts/option/thumbnail.py
ipecharts/option/timeline.py
ipecharts/option/title.py
ipecharts/option/toolbox.py
ipecharts/option/tooltip.py
ipecharts/option/visualmap.py
ipecharts/option/xaxis.py
ipecharts/option/xaxis3d.py
ipecharts/option/yaxis.py
ipecharts/option/yaxis3d.py
ipecharts/option/zaxis3d.py
ipecharts/option/datazoomitems/__init__.py
ipecharts/option/datazoomitems/inside.py
ipecharts/option/datazoomitems/slider.py
ipecharts/option/mediaitems/__init__.py
ipecharts/option/mediaitems/mediaitem.py
ipecharts/option/seriesitems/__init__.py
ipecharts/option/seriesitems/bar.py
ipecharts/option/seriesitems/bar3d.py
ipecharts/option/seriesitems/boxplot.py
ipecharts/option/seriesitems/candlestick.py
ipecharts/option/seriesitems/custom.py
ipecharts/option/seriesitems/effectscatter.py
ipecharts/option/seriesitems/flowgl.py
ipecharts/option/seriesitems/funnel.py
ipecharts/option/seriesitems/gauge.py
ipecharts/option/seriesitems/graph.py
ipecharts/option/seriesitems/graphgl.py
ipecharts-1.4.0.dist-info/METADATA
ipecharts-1.4.0.dist-info/WHEEL
ipecharts-1.4.0.dist-info/licenses/LICENSE
ipecharts-1.4.0.dist-info/RECORD
