Metadata-Version: 2.4
Name: ipecharts
Version: 1.4.0
Dynamic: Keywords
Summary: Apache Echarts Jupyter Widget.
Project-URL: Homepage, https://github.com/trungleduc/ipecharts
Project-URL: Bug Tracker, https://github.com/trungleduc/ipecharts/issues
Project-URL: Repository, https://github.com/trungleduc/ipecharts.git
Author-email: Trung Le <leductrungxf@gmail.com>
License: BSD 3-Clause License
License-File: LICENSE
Classifier: Framework :: Jupyter
Classifier: Framework :: Jupyter :: JupyterLab
Classifier: Framework :: Jupyter :: JupyterLab :: 4
Classifier: Framework :: Jupyter :: JupyterLab :: Extensions
Classifier: Framework :: Jupyter :: JupyterLab :: Extensions :: Prebuilt
Classifier: License :: OSI Approved :: BSD License
Classifier: Programming Language :: Python
Classifier: Programming Language :: Python :: 3
Classifier: Programming Language :: Python :: 3.8
Classifier: Programming Language :: Python :: 3.9
Classifier: Programming Language :: Python :: 3.10
Classifier: Programming Language :: Python :: 3.11
Requires-Python: >=3.8
Requires-Dist: ipywidgets<9,>=8
